mesa/MESA.py
mesa/__init__.py
mesa_cfdna-0.6.0.dist-info/licenses/LICENSE
mesa_cfdna-0.6.0.dist-info/METADATA
mesa_cfdna-0.6.0.dist-info/WHEEL
mesa_cfdna-0.6.0.dist-info/top_level.txt
mesa_cfdna-0.6.0.dist-info/RECORD
