Metadata-Version: 2.4
Name: mesa_cfdna
Version: 0.6.0
Summary: Multimodal Epigenetic Sequencing Analysis (MESA) is a flexible and sensitive method of capturing and integrating multimodal epigenetic information of cfDNA using a single experimental assay.
Home-page: https://github.com/ChaorongC/mesa_cfdna
Author: Chaorong Chen
Author-email: c.chen@uci.edu
License: BSD 3 clause
Keywords: feature selection,machine learning,random forest,bioinformatic,multimodal,epigenetics,genomics,cancer detection
Requires-Python: >=3.6
License-File: LICENSE
Requires-Dist: numpy>=1.10.4
Requires-Dist: scikit-learn>=0.17.1
Requires-Dist: scipy>=0.17.0
Requires-Dist: Boruta
Requires-Dist: pandas
Requires-Dist: joblib
Requires-Dist: scipy
Dynamic: author
Dynamic: author-email
Dynamic: description
Dynamic: description-content-type
Dynamic: home-page
Dynamic: keywords
Dynamic: license
Dynamic: license-file
Dynamic: requires-dist
Dynamic: requires-python
Dynamic: summary
